cscoder/__init__.py
cscoder/coder.py
cscoder/preprocess.py
cscoder/utils.py
cscoder/data/cncity.csv
cscoder/data/csco22.csv
cscoder/data/stopwords.txt
cscoder/data/testcases.csv
cscoder-0.2.4.dist-info/METADATA
cscoder-0.2.4.dist-info/WHEEL
cscoder-0.2.4.dist-info/entry_points.txt
cscoder-0.2.4.dist-info/top_level.txt
cscoder-0.2.4.dist-info/RECORD
