Metadata-Version: 2.4
Name: cscoder
Version: 0.2.4
Summary: A Python package for matching unstructure job titles with China Standard Classifications of Occupations (CSCO).
Author-email: Antao Li <anthony.li.antao@outlook.com>
License: MIT
Project-URL: Homepage, https://github.com/anthonyliantao/cscoder
Classifier: Development Status :: 3 - Alpha
Classifier: Intended Audience :: Developers
Classifier: License :: OSI Approved :: MIT License
Classifier: Programming Language :: Python :: 3
Classifier: Programming Language :: Python :: 3.8
Classifier: Programming Language :: Python :: 3.9
Classifier: Programming Language :: Python :: 3.10
Requires-Python: >=3.8
Requires-Dist: importlib-resources; python_version < "3.9"
Requires-Dist: sentence-transformers
Requires-Dist: scipy
Requires-Dist: numpy
Requires-Dist: pandas
Requires-Dist: tqdm
Provides-Extra: dev
Requires-Dist: black; extra == "dev"
Requires-Dist: flake8; extra == "dev"
Requires-Dist: pytest; extra == "dev"
